rosia/__init__.py
rosia/comms/Types.py
rosia/comms/serializers/__init__.py
rosia/comms/serializers/base.py
rosia/comms/serializers/cloudpickle.py
rosia/comms/serializers/pickle.py
rosia/comms/serializers/pickle5.py
rosia/comms/transports/__init__.py
rosia/comms/transports/base.py
rosia/comms/transports/zmq_transport.py
rosia/coordinate/Coordinator.py
rosia/coordinate/Node.py
rosia/coordinate/Port.py
rosia/coordinate/__init__.py
rosia/coordinate/messages/base.py
rosia/execute/Executor.py
rosia/execute/__init__.py
rosia/frontend/Node.py
rosia/frontend/Port.py
rosia/frontend/__init__.py
rosia/time/Time.py
rosia/time/Timer.py
rosia/time/__init__.py
rosia-0.0.4.dist-info/licenses/LICENSE
rosia-0.0.4.dist-info/METADATA
rosia-0.0.4.dist-info/WHEEL
rosia-0.0.4.dist-info/top_level.txt
rosia-0.0.4.dist-info/RECORD
