Metadata-Version: 2.4
Name: rosia
Version: 0.0.4
Summary: A robotic middleware in Python.
Author-email: depetrol <depetrol@outlook.com>
License-Expression: Apache-2.0
Project-URL: Homepage, https://github.com/rosia-project/rosia
Project-URL: Issues, https://github.com/rosia-project/rosia/issues
Classifier: Programming Language :: Python :: 3
Classifier: Operating System :: OS Independent
Requires-Python: >=3.9
License-File: LICENSE
Requires-Dist: pyzmq
Requires-Dist: cloudpickle
Dynamic: license-file
